LICENSE
README.md
pyproject.toml
karuocv/__init__.py
karuocv/client.py
karuocv/utils.py
karuocv.egg-info/PKG-INFO
karuocv.egg-info/SOURCES.txt
karuocv.egg-info/dependency_links.txt
karuocv.egg-info/entry_points.txt
karuocv.egg-info/requires.txt
karuocv.egg-info/top_level.txt
karuocv/hub/datautils.py
karuocv/hub/inference.py
karuocv/hub/sample_handle.py
karuocv/hub/sample_watch.py
karuocv/tools/debugtool.py
karuocv/tools/validatortool.py
karuocv/unstable/pyonnx.py
tests/test_samples_handler.py